mOTUlizer/__init__.py
mOTUlizer/config.py
mOTUlizer/process_colicogs.py
mOTUlizer/run.py
mOTUlizer/scratch.py
mOTUlizer/uppmax.py
mOTUlizer/utils.py
mOTUlizer/bin/__init__.py
mOTUlizer/bin/mOTUconvert.py
mOTUlizer/bin/mOTUlize.py
mOTUlizer/bin/mOTUpan.py
mOTUlizer/classes/COGs.py
mOTUlizer/classes/MetaBin.py
mOTUlizer/classes/MockData.py
mOTUlizer/classes/Parser.py
mOTUlizer/classes/__init__.py
mOTUlizer/classes/mOTU.py
mOTUlizer/scripts/__init__.py
mOTUlizer/scripts/prochloros.py
mOTUlizer-0.3.2.data/scripts/anvi-script-compute-bayesian-pan-core
mOTUlizer-0.3.2.data/scripts/mOTUconvert.py
mOTUlizer-0.3.2.data/scripts/mOTUlize.py
mOTUlizer-0.3.2.data/scripts/mOTUpan.py
mOTUlizer-0.3.2.dist-info/LICENSE
mOTUlizer-0.3.2.dist-info/METADATA
mOTUlizer-0.3.2.dist-info/WHEEL
mOTUlizer-0.3.2.dist-info/top_level.txt
mOTUlizer-0.3.2.dist-info/RECORD
