Metadata-Version: 2.1
Name: mOTUlizer
Version: 0.3.2
Summary: making OTUs from genomes, and stats on them. and even core-genomes
Home-page: https://github.com/moritzbuck/mOTUlizer/
Author: Moritz Buck
Author-email: moritz.buck@slu.se
License: UNKNOWN
Keywords: bioinformatics clustering metagenomics microbial-genomics genomics
Platform: UNKNOWN
Classifier: Programming Language :: Python :: 3
Classifier: License :: OSI Approved :: GNU General Public License v3 (GPLv3)
Classifier: Operating System :: OS Independent
Classifier: Intended Audience :: Science/Research
Classifier: Topic :: Scientific/Engineering :: Bio-Informatics
Requires-Python: >=3.6
License-File: LICENSE
Requires-Dist: python-igraph
Requires-Dist: biopython
